[{"instructions/2/position": "instructions/2/position", "directiveIdeas": "directiveIdeas", "instructions/1/action": "instructions/1/action", "instructions/2/action": "instructions/2/action", "instructions/0/action": "instructions/0/action", "instructions/1/position": "instructions/1/position", "stepNumber": "stepNumber", "instructions/0/position": "instructions/0/position"}, {"instructions/2/position": "", "directiveIdeas": "", "instructions/1/action": "Halt, Salute", "instructions/2/action": "Proceed in working trot", "instructions/0/action": "Enter in working trot", "instructions/1/position": "X", "stepNumber": "1", "instructions/0/position": "A"}, {"instructions/2/position": "HB", "directiveIdeas": "", "instructions/1/action": "Half circle left 10m returning to the track at H", "instructions/2/action": "Working trot", "instructions/0/action": "Track left", "instructions/1/position": "EX", "stepNumber": "2", "instructions/0/position": "C"}, {"instructions/2/position": "", "directiveIdeas": "", "instructions/1/action": "Working trot", "instructions/2/action": "", "instructions/0/action": "Half circle right 10m, returning to the track at M", "instructions/1/position": "MC", "stepNumber": "3", "instructions/0/position": "BX"}, {"instructions/2/position": "CH", "directiveIdeas": "", "instructions/1/action": "Shorten the reins", "instructions/2/action": "Working trot", "instructions/0/action": "Circle left 20m rising trot, allowing the horse to stretch forward and downward while maintaining contact", "instructions/1/position": "Before C", "stepNumber": "4", "instructions/0/position": "C"}, {"instructions/2/position": "", "directiveIdeas": "", "instructions/1/action": "Working trot", "instructions/2/action": "", "instructions/0/action": "Change rein, lengthen stride in trot", "instructions/1/position": "PA", "stepNumber": "5", "instructions/0/position": "HP"}, {"instructions/2/position": "", "directiveIdeas": "", "instructions/1/action": "", "instructions/2/action": "", "instructions/0/action": "Medium walk", "instructions/1/position": "", "stepNumber": "6", "instructions/0/position": "AV"}, {"instructions/2/position": "", "directiveIdeas": "", "instructions/1/action": "Medium walk", "instructions/2/action": "", "instructions/0/action": "Change rein, free walk on a long rein", "instructions/1/position": "RM", "stepNumber": "7", "instructions/0/position": "VR"}, {"instructions/2/position": "CH", "directiveIdeas": "", "instructions/1/action": "Working canter left lead", "instructions/2/action": "Working canter", "instructions/0/action": "Working trot", "instructions/1/position": "C", "stepNumber": "8", "instructions/0/position": "M"}, {"instructions/2/position": "", "directiveIdeas": "", "instructions/1/action": "", "instructions/2/action": "", "instructions/0/action": "Lengthen stride in canter", "instructions/1/position": "", "stepNumber": "9", "instructions/0/position": "HV"}, {"instructions/2/position": "", "directiveIdeas": "", "instructions/1/action": "Working canter", "instructions/2/action": "", "instructions/0/action": "Circle left 15m Develop working canter in first half of circle", "instructions/1/position": "VF", "stepNumber": "10", "instructions/0/position": "VR"}, {"instructions/2/position": "HC", "directiveIdeas": "", "instructions/1/action": "Working trot", "instructions/2/action": "Working trot", "instructions/0/action": "Change rein", "instructions/1/position": "X", "stepNumber": "11", "instructions/0/position": "FXH"}, {"instructions/2/position": "", "directiveIdeas": "", "instructions/1/action": "Working canter", "instructions/2/action": "", "instructions/0/action": "Working canter right lead", "instructions/1/position": "CM", "stepNumber": "12", "instructions/0/position": "C"}, {"instructions/2/position": "", "directiveIdeas": "", "instructions/1/action": "", "instructions/2/action": "", "instructions/0/action": "Lengthen stride in canter", "instructions/1/position": "", "stepNumber": "13", "instructions/0/position": "MP"}, {"instructions/2/position": "", "directiveIdeas": "", "instructions/1/action": "Working canter", "instructions/2/action": "", "instructions/0/action": "Circle right 15m Develop working canter in first half of circle", "instructions/1/position": "PA", "stepNumber": "14", "instructions/0/position": "P"}, {"instructions/2/position": "", "directiveIdeas": "", "instructions/1/action": "", "instructions/2/action": "", "instructions/0/action": "Working trot", "instructions/1/position": "", "stepNumber": "15", "instructions/0/position": "AK"}, {"instructions/2/position": "", "directiveIdeas": "", "instructions/1/action": "Working trot", "instructions/2/action": "", "instructions/0/action": "Change rein, lengthen stride in trot", "instructions/1/position": "RE", "stepNumber": "16", "instructions/0/position": "KR"}, {"instructions/2/position": "G", "directiveIdeas": "", "instructions/1/action": "Down centreline", "instructions/2/action": "Halt salute", "instructions/0/action": "Half circle left 10m", "instructions/1/position": "X", "stepNumber": "17", "instructions/0/position": "E"}, {"instructions/2/position": "", "directiveIdeas": "", "instructions/1/action": "", "instructions/2/action": "", "instructions/0/action": "", "instructions/1/position": "", "stepNumber": "", "instructions/0/position": ""}, {"instructions/2/position": "", "directiveIdeas": "", "instructions/1/action": "", "instructions/2/action": "", "instructions/0/action": "", "instructions/1/position": "", "stepNumber": "First Level Test 1", "instructions/0/position": ""}]